jtim_enc/__init__.py
jtim_enc/encryptor.py
jtim_enc-0.1.dist-info/METADATA
jtim_enc-0.1.dist-info/WHEEL
jtim_enc-0.1.dist-info/top_level.txt
jtim_enc-0.1.dist-info/RECORD
