Metadata-Version: 2.1
Name: jtim-enc
Version: 0.1
Summary: Randomized Base64 codec
Home-page: https://gitlab.com/jeefies/jtim-enc
Author: Jeefy
Author-email: jeefy163@163.com
Classifier: Programming Language :: Python :: 3
Classifier: License :: OSI Approved :: MIT License
Classifier: Operating System :: OS Independent
Requires-Python: >=3.6
